yt_toolkit/__init__.py
yt_toolkit/src/__init__.py
yt_toolkit/src/heatmap_tools.py
yt_toolkit/src/transcripts.py
yt_toolkit/src/video_scraping.py
yt_toolkit/src/yt_api.py
yt_toolkit/test/__init__.py
yt_toolkit/test/test_basic.py
yt_toolkit-0.1.5.dist-info/LICENSE.txt
yt_toolkit-0.1.5.dist-info/METADATA
yt_toolkit-0.1.5.dist-info/WHEEL
yt_toolkit-0.1.5.dist-info/top_level.txt
yt_toolkit-0.1.5.dist-info/RECORD
