Metadata-Version: 2.1
Name: yt-toolkit
Version: 0.1.5
Summary: A library for retrieving and processing YouTube data (API, scraping, transcripts, heatmaps).
Home-page: https://github.com/MartaAlet/yt-toolkit
Author: MartaAlet
Author-email: m.aletpuig@gmail.com
License: MIT
Classifier: License :: OSI Approved :: MIT License
Classifier: Programming Language :: Python :: 3.11
Classifier: Operating System :: OS Independent
Requires-Python: >=3.11
License-File: LICENSE.txt
Requires-Dist: google-api-python-client (>=2.0.0)
Requires-Dist: google-auth (>=2.0.0)
Requires-Dist: selenium (>=4.0.0)
Requires-Dist: beautifulsoup4 (>=4.9.0)
Requires-Dist: lxml (>=4.6.0)
Requires-Dist: youtube-transcript-api (>=0.4.0)
Requires-Dist: svgpathtools (>=1.4.0)
Requires-Dist: trio-websocket (==0.11.1)
